epub_translator/__init__.py
epub_translator/data/fill.jinja
epub_translator/data/mmltex/README.md
epub_translator/data/mmltex/cmarkup.xsl
epub_translator/data/mmltex/entities.xsl
epub_translator/data/mmltex/glayout.xsl
epub_translator/data/mmltex/mmltex.xsl
epub_translator/data/mmltex/scripts.xsl
epub_translator/data/mmltex/tables.xsl
epub_translator/data/mmltex/tokens.xsl
epub_translator/data/translate.jinja
epub_translator/epub/__init__.py
epub_translator/epub/common.py
epub_translator/epub/math.py
epub_translator/epub/metadata.py
epub_translator/epub/spines.py
epub_translator/epub/toc.py
epub_translator/epub/zip.py
epub_translator/llm/__init__.py
epub_translator/llm/context.py
epub_translator/llm/core.py
epub_translator/llm/error.py
epub_translator/llm/executor.py
epub_translator/llm/increasable.py
epub_translator/llm/types.py
epub_translator/segment/__init__.py
epub_translator/segment/block_segment.py
epub_translator/segment/common.py
epub_translator/segment/inline_segment.py
epub_translator/segment/text_segment.py
epub_translator/segment/utils.py
epub_translator/serial/__init__.py
epub_translator/serial/chunk.py
epub_translator/serial/segment.py
epub_translator/serial/splitter.py
epub_translator/template.py
epub_translator/translation/__init__.py
epub_translator/translation/epub_transcode.py
epub_translator/translation/language.py
epub_translator/translation/punctuation.py
epub_translator/translation/translator.py
epub_translator/translation/xml_interrupter.py
epub_translator/utils.py
epub_translator/xml/__init__.py
epub_translator/xml/const.py
epub_translator/xml/deduplication.py
epub_translator/xml/friendly/__init__.py
epub_translator/xml/friendly/decoder.py
epub_translator/xml/friendly/encoder.py
epub_translator/xml/friendly/parser.py
epub_translator/xml/friendly/tag.py
epub_translator/xml/friendly/transform.py
epub_translator/xml/inline.py
epub_translator/xml/self_closing.py
epub_translator/xml/utils.py
epub_translator/xml/xml.py
epub_translator-0.1.6.dist-info/LICENSE
epub_translator-0.1.6.dist-info/METADATA
epub_translator-0.1.6.dist-info/WHEEL
epub_translator-0.1.6.dist-info/RECORD
