Metadata-Version: 2.3
Name: epub-translator
Version: 0.1.6
Summary: Translate the epub book using LLM. The translated book will retain the original text and list the translated text side by side with the original text.
License: MIT
Keywords: epub,llm,translation,translator
Author: Tao Zeyu
Author-email: i@taozeyu.com
Maintainer: Tao Zeyu
Maintainer-email: i@taozeyu.com
Requires-Python: >=3.11,<3.14
Classifier: Development Status :: 4 - Beta
Classifier: Intended Audience :: Developers
Classifier: Intended Audience :: Education
Classifier: Intended Audience :: Science/Research
Classifier: License :: OSI Approved :: MIT License
Classifier: Operating System :: OS Independent
Classifier: Programming Language :: Python :: 3
Classifier: Programming Language :: Python :: 3.11
Classifier: Programming Language :: Python :: 3.12
Classifier: Programming Language :: Python :: 3.13
Classifier: Topic :: Software Development :: Libraries :: Python Modules
Classifier: Topic :: Software Development :: Localization
Classifier: Topic :: Text Processing :: Markup
Classifier: Topic :: Scientific/Engineering :: Artificial Intelligence
Requires-Dist: jinja2 (>=3.1.6,<4.0.0)
Requires-Dist: openai (>=2.14.0,<3.0.0)
Requires-Dist: resource-segmentation (>=0.0.7,<0.1.0)
Requires-Dist: tiktoken (>=0.12.0,<1.0.0)
Project-URL: Homepage, https://hub.oomol.com/package/books-translator
Project-URL: Repository, https://github.com/oomol-lab/epub-translator
